tornasess
