Metadata-Version: 1.1
Name: tornasess
Version: 0.6
Summary: A tornado session implementation
Home-page: https://github.com/free-free/tornasess
Author: HuangBiao
Author-email: 19941222hb@gmail.com
License: MIT
Keywords: tornado,session
Platform: UNKNOWN
Classifier: Intended Audience :: Developers
Classifier: License :: OSI Approved :: MIT License
Classifier: Programming Language :: Python
Classifier: Programming Language :: Python :: 3
Classifier: Programming Language :: Python :: 3.3
Classifier: Programming Language :: Python :: 3.4
Classifier: Programming Language :: Python :: 3.5
Classifier: Topic :: Software Development :: Libraries :: Python Modules
Classifier: Topic :: Internet :: WWW/HTTP :: Dynamic Content
